dynamicdns/__init__.py
dynamicdns/admin.py
dynamicdns/models.py
dynamicdns/urls.py
dynamicdns/utils.py
dynamicdns/views.py
dynamicdns/management/__init__.py
dynamicdns/management/commands/__init__.py
dynamicdns/management/commands/run_dns_server.py
dynamicdns/migrations/0001_initial.py
dynamicdns/migrations/__init__.py
dynamicdns/plugins/__init__.py
dynamicdns/plugins/digitalocean.py
dynamicdns/plugins/dummy.py
dynamicdns/plugins/rackspace.py
django_dynamic_dns-0.1.4.dist-info/LICENSE.txt
django_dynamic_dns-0.1.4.dist-info/METADATA
django_dynamic_dns-0.1.4.dist-info/WHEEL
django_dynamic_dns-0.1.4.dist-info/top_level.txt
django_dynamic_dns-0.1.4.dist-info/RECORD
